soundfonttools/demo/demoSoundFont.sf2
soundfonttools/demo/sFAnalyser_demo.cfg
soundfonttools/demo/sFInPlaceRenamer_demo.cfg
soundfonttools/doc/soundFontTools-documentation.pdf
soundfonttools/src/__init__.py
soundfonttools/src/_main/jsontosoundfont.py
soundfonttools/src/_main/simplefunctions.py
soundfonttools/src/_main/soundfontanalyser.py
soundfonttools/src/_main/soundfontinplacerenamer.py
soundfonttools/src/_main/soundfonttojson.py
soundfonttools/src/basemodules/__init__.py
soundfonttools/src/basemodules/configurationfile.py
soundfonttools/src/basemodules/operatingsystem.py
soundfonttools/src/basemodules/simpleassertion.py
soundfonttools/src/basemodules/simplelogging.py
soundfonttools/src/basemodules/simpletypes.py
soundfonttools/src/basemodules/stringutil.py
soundfonttools/src/basemodules/ttbase.py
soundfonttools/src/basemodules/typesupport.py
soundfonttools/src/basemodules/validitychecker.py
soundfonttools/src/multimedia/__init__.py
soundfonttools/src/multimedia/audio/__init__.py
soundfonttools/src/multimedia/audio/wavefile.py
soundfonttools/src/multimedia/midi/__init__.py
soundfonttools/src/multimedia/midi/soundfont.py
soundfonttools/src/multimedia/midi/soundfontfile.py
soundfonttools-0.1.4.dist-info/licenses/LICENSE.txt
soundfonttools-0.1.4.dist-info/METADATA
soundfonttools-0.1.4.dist-info/WHEEL
soundfonttools-0.1.4.dist-info/entry_points.txt
soundfonttools-0.1.4.dist-info/top_level.txt
soundfonttools-0.1.4.dist-info/RECORD
