Metadata-Version: 2.4
Name: soundfonttools
Version: 0.1.4
Summary: Analysis and Conversion Tools for SoundFonts
Author-email: "Dr. Thomas Tensi" <t.tensi@gmx.de>
License-Expression: MIT
Project-URL: homepage, https://github.com/prof-spock/SoundFontTools
Project-URL: repository, https://github.com/prof-spock/SoundFontTools
Keywords: audio,soundfont,json,analysis,conversion
Classifier: Development Status :: 4 - Beta
Classifier: Environment :: Console
Classifier: Intended Audience :: Developers
Classifier: Natural Language :: English
Classifier: Programming Language :: Python :: 3.10
Classifier: Topic :: Multimedia :: Sound/Audio :: MIDI
License-File: LICENSE.txt
Dynamic: license-file
